MANIFEST.in
setup.cfg
setup.py
eventum/__init__.py
eventum/__init__.pyc
eventum/authorize.py
eventum.egg-info/PKG-INFO
eventum.egg-info/SOURCES.txt
eventum.egg-info/dependency_links.txt
eventum.egg-info/not-zip-safe
eventum.egg-info/requires.txt
eventum.egg-info/top_level.txt
eventum/config/__init__.py
eventum/config/__init__.pyc
eventum/config/eventum_config.py
eventum/config/eventum_config.pyc
eventum/forms/AddToWhitelistForm.py
eventum/forms/AddToWhitelistForm.pyc
eventum/forms/CreateBlogPostForm.py
eventum/forms/CreateBlogPostForm.pyc
eventum/forms/CreateEventForm.py
eventum/forms/CreateEventForm.pyc
eventum/forms/CreateProfileForm.py
eventum/forms/CreateProfileForm.pyc
eventum/forms/DeleteEventForm.py
eventum/forms/DeleteEventForm.pyc
eventum/forms/EditEventForm.py
eventum/forms/EditEventForm.pyc
eventum/forms/EditUserForm.py
eventum/forms/EditUserForm.pyc
eventum/forms/README.md
eventum/forms/UploadImageForm.py
eventum/forms/UploadImageForm.pyc
eventum/forms/__init__.py
eventum/forms/__init__.pyc
eventum/forms/validators.py
eventum/forms/validators.pyc
eventum/forms/fields/README.md
eventum/forms/fields/TimeField.py
eventum/forms/fields/TimeField.pyc
eventum/forms/fields/__init__.py
eventum/forms/fields/__init__.pyc
eventum/lib/README.md
eventum/lib/__init__.py
eventum/lib/__init__.pyc
eventum/lib/decorators.py
eventum/lib/decorators.pyc
eventum/lib/error.py
eventum/lib/error.pyc
eventum/lib/events.py
eventum/lib/events.pyc
eventum/lib/google_calendar.py
eventum/lib/google_calendar.pyc
eventum/lib/google_calendar_resource_builder.py
eventum/lib/google_calendar_resource_builder.pyc
eventum/lib/google_web_server_auth.py
eventum/lib/google_web_server_auth.pyc
eventum/lib/json_response.py
eventum/lib/json_response.pyc
eventum/lib/regex.py
eventum/lib/regex.pyc
eventum/lib/text.py
eventum/lib/text.pyc
eventum/models/BaseEventumDocument.py
eventum/models/BaseEventumDocument.pyc
eventum/models/BlogPost.py
eventum/models/BlogPost.pyc
eventum/models/Event.py
eventum/models/Event.pyc
eventum/models/EventSeries.py
eventum/models/EventSeries.pyc
eventum/models/Image.py
eventum/models/Image.pyc
eventum/models/Post.py
eventum/models/Post.pyc
