Metadata-Version: 1.0
Name: eventum
Version: 0.2.7
Summary: A content management system for event-driven Flask apps
Home-page: http://github.com/danrschlosser/eventum
Author: Dan Schlosser
Author-email: dan@schlosser.io
License: MIT
Platform: UNKNOWN
